cartographer/__init__.py
cartographer/__version__.py
cartographer/core.py
cartographer/extra.py
cartographer/stream.py
cartographer/toolhead.py
cartographer/adapters/__init__.py
cartographer/adapters/utils.py
cartographer/adapters/kalico/__init__.py
cartographer/adapters/kalico/adapters.py
cartographer/adapters/kalico/integrator.py
cartographer/adapters/kalico/probe.py
cartographer/adapters/klipper/__init__.py
cartographer/adapters/klipper/adapters.py
cartographer/adapters/klipper/axis_twist_compensation.py
cartographer/adapters/klipper/bed_mesh.py
cartographer/adapters/klipper/configuration.py
cartographer/adapters/klipper/endstop.py
cartographer/adapters/klipper/gcode.py
cartographer/adapters/klipper/homing.py
cartographer/adapters/klipper/integrator.py
cartographer/adapters/klipper/logging.py
cartographer/adapters/klipper/probe.py
cartographer/adapters/klipper/task_executor.py
cartographer/adapters/klipper/temperature.py
cartographer/adapters/klipper/toolhead.py
cartographer/adapters/klipper/mcu/__init__.py
cartographer/adapters/klipper/mcu/async_processor.py
cartographer/adapters/klipper/mcu/commands.py
cartographer/adapters/klipper/mcu/constants.py
cartographer/adapters/klipper/mcu/mcu.py
cartographer/adapters/klipper/mcu/stream.py
cartographer/adapters/klipper_like/integrator.py
cartographer/coil/calibration.py
cartographer/coil/helpers.py
cartographer/coil/temperature_compensation.py
cartographer/config/__init__.py
cartographer/config/parser.py
cartographer/interfaces/__init__.py
cartographer/interfaces/configuration.py
cartographer/interfaces/multiprocessing.py
cartographer/interfaces/printer.py
cartographer/lib/alpha_beta_filter.py
cartographer/lib/csv.py
cartographer/lib/log.py
cartographer/lib/nearest_neighbor.py
cartographer/lib/scipy_helpers.py
cartographer/lib/statistics.py
cartographer/lib/str.py
cartographer/macros/__init__.py
cartographer/macros/axis_twist_compensation.py
cartographer/macros/backlash.py
cartographer/macros/migration_message.py
cartographer3d_plugin-2.0.0.dist-info/METADATA
cartographer3d_plugin-2.0.0.dist-info/WHEEL
cartographer3d_plugin-2.0.0.dist-info/licenses/LICENSE
cartographer3d_plugin-2.0.0.dist-info/extra_metadata/release_info
cartographer3d_plugin-2.0.0.dist-info/RECORD
