Metadata-Version: 2.4
Name: cartographer3d-plugin
Version: 2.0.0
Summary: An extras for klipper to integrate with cartographer
Project-URL: homepage, https://cartographer3d.com/
Project-URL: repository, https://github.com/Cartographer3D/cartographer3d-plugin
License:                     GNU GENERAL PUBLIC LICENSE
License-File: LICENSE
Keywords: 3D printing,cartographer,klipper
Classifier: Development Status :: 3 - Alpha
Classifier: Intended Audience :: End Users/Desktop
Classifier: License :: OSI Approved :: GNU General Public License v3 (GPLv3)
Requires-Python: <4,>=3.8
Requires-Dist: typing-extensions~=4.12
Provides-Extra: scipy
Requires-Dist: scipy~=1.9; extra == 'scipy'
